langworks/__init__.py
langworks/config.py
langworks/langwork.py
langworks/messages.py
langworks/query.py
langworks/dsl/__init__.py
langworks/dsl/environment.py
langworks/dsl/constraints/__init__.py
langworks/dsl/constraints/base.py
langworks/dsl/constraints/cache.py
langworks/dsl/constraints/choice.py
langworks/dsl/constraints/dataclass.py
langworks/dsl/constraints/gen.py
langworks/dsl/constraints/grammar_gbnf.py
langworks/dsl/constraints/grammar_lark.py
langworks/dsl/constraints/json.py
langworks/dsl/constraints/regex.py
langworks/middleware/__init__.py
langworks/middleware/balancer.py
langworks/middleware/generic.py
langworks/middleware/llama_cpp.py
langworks/middleware/vllm.py
langworks/util/__init__.py
langworks/util/auth.py
langworks/util/balancing.py
langworks/util/caching.py
langworks/util/json.py
langworks/util/string.py
langworks-0.3.1.dist-info/licenses/LICENSE
langworks-0.3.1.dist-info/METADATA
langworks-0.3.1.dist-info/WHEEL
langworks-0.3.1.dist-info/top_level.txt
langworks-0.3.1.dist-info/RECORD
