Metadata-Version: 2.4
Name: langworks
Version: 0.3.1
Summary: Flexibly instruct and prompt LLMs in Python
Author: Rosaia B.V.
License: 
Project-URL: Documentation, https://rosaia.github.io/langworks/
Project-URL: Repository, https://github.com/rosaia/langworks
Project-URL: Changelog, https://github.com/rosaia/langworks/blob/main/CHANGELOG.md
Keywords: large language models,LLMs,prompt engineering,guided generation
Classifier: Development Status :: 4 - Beta
Classifier: License :: OSI Approved :: Apache Software License
Classifier: Programming Language :: Python :: 3
Classifier: Operating System :: OS Independent
Classifier: Topic :: Software Development :: Libraries
Requires-Python: >=3.11
License-File: LICENSE
Requires-Dist: cachetools>=5.3
Requires-Dist: jinja2>=3.1
Requires-Dist: jinja2_simple_tags>=0.6.1
Requires-Dist: pypeworks>=0.3.1
Requires-Dist: typing-extensions>=4.8.0
Provides-Extra: llamacpp
Requires-Dist: openai>=1.17; extra == "llamacpp"
Provides-Extra: vllm
Requires-Dist: openai>=1.17; extra == "vllm"
Dynamic: license-file
